{
  "ComponentIndexes": {},
  "ControlUniqueIds": {
    "App": 1,
    "Attachments_DataCard2": 104,
    "Body4_1": 150,
    "Body4_10": 148,
    "Body4_2": 158,
    "Body4_3": 157,
    "Body4_4": 146,
    "Body4_5": 154,
    "Body4_6": 145,
    "Body4_7": 151,
    "Body4_8": 155,
    "Body4_9": 147,
    "btnSave_1": 153,
    "btnSave_10": 113,
    "btnSave_11": 114,
    "btnSave_12": 191,
    "btnSave_13": 110,
    "btnSave_14": 106,
    "btnSave_15": 47,
    "btnSave_2": 175,
    "btnSave_3": 229,
    "btnSave_4": 233,
    "btnSave_7": 74,
    "btnSave_8": 75,
    "btnSave_9": 115,
    "btnSaveLibRec": 219,
    "Button1": 138,
    "Button1_1": 199,
    "CB_Responsible": 72,
    "chkSelectItem": 200,
    "Cost Code Screen": 3,
    "dcAttachments": 105,
    "dd_Revision": 218,
    "dpDalReqDate": 101,
    "drpgalCat": 98,
    "drpgalCat_CCS": 46,
    "drpgalCostCode": 97,
    "drpgalCostCode_CCS": 45,
    "drpgalReq": 102,
    "drpgalUOM": 96,
    "drpgalUOM_4": 196,
    "drpgalUOM_5": 213,
    "drpgalUOM_6": 214,
    "drpgalVendor": 89,
    "drpgalVendor_CCS": 40,
    "frmAttachments": 103,
    "galAddReqItems": 84,
    "galAvailableReqItems": 65,
    "galAvailableReqItems_1": 26,
    "galCCAttachments": 11,
    "Gallery2": 33,
    "galleryTemplate1": 12,
    "galleryTemplate1_1": 178,
    "galleryTemplate2": 198,
    "galleryTemplate3": 34,
    "galleryTemplate5": 137,
    "galleryTemplate6": 162,
    "galleryTemplate7": 85,
    "galleryTemplate8": 66,
    "galleryTemplate8_1": 27,
    "galLibraryItems": 197,
    "galMessages": 177,
    "galReqDetails": 161,
    "galRequisitions": 136,
    "Group3": 225,
    "grp_AddREqDetails": 126,
    "grp_Header_LS": 223,
    "grp_Header_LS_1": 183,
    "grp_Header_MS": 122,
    "grp_Header_RS_1": 167,
    "grp_Header_RS_2": 50,
    "grp_SendEmail": 184,
    "grp_SendEmail_1": 232,
    "grp_SendEmail_2": 236,
    "grpAddReq": 125,
    "grpAddReqDetails": 51,
    "grpCloseAttach": 129,
    "grpGTLib_MS": 124,
    "grpGTReq_MS": 123,
    "grpSaveReq": 127,
    "grpSaveReqDetails": 226,
    "grpSaveStatus_4": 128,
    "grpSearch": 224,
    "icnAddItems": 189,
    "icnAddNewReq": 62,
    "icnCollapse": 143,
    "icnCollapse_Lib": 203,
    "icnExpand": 142,
    "icnExpand_Lib": 202,
    "icnSave": 221,
    "icnSearch": 216,
    "Icon1_10": 118,
    "Icon1_11": 107,
    "Image1": 194,
    "Image1_1": 186,
    "Image1_10": 117,
    "Image1_2": 169,
    "Image1_3": 131,
    "Image1_6": 4,
    "Image1_8": 53,
    "Image1_9": 116,
    "Image10": 139,
    "Image14_3": 56,
    "Image2_1": 192,
    "Image2_2": 228,
    "Image3": 35,
    "Image3_1": 36,
    "Image4": 25,
    "Image6": 149,
    "Image6_1": 152,
    "Image6_2": 156,
    "Image8": 174,
    "Image8_1": 230,
    "Image8_2": 234,
    "Image8_3": 77,
    "Image8_4": 78,
    "Image8_5": 109,
    "Image8_6": 48,
    "Image9": 179,
    "Image9_1": 182,
    "imd_DelRec": 69,
    "imd_DelRec_1": 70,
    "imd_DelRec_2": 31,
    "imgShowCurrentReqDetails": 60,
    "Label1": 195,
    "Label1_1": 188,
    "Label1_2": 171,
    "Label1_3": 133,
    "Label1_4": 6,
    "Label1_6": 55,
    "Label1_8": 108,
    "Label2": 76,
    "Label2_1": 49,
    "Label2_2": 172,
    "Label2_3": 176,
    "Label2_4": 193,
    "Label2_5": 211,
    "Label2_6": 212,
    "Label2_7": 231,
    "Label2_8": 235,
    "Label3_2": 119,
    "Label3_3": 120,
    "Label3_4": 121,
    "Label3_5": 111,
    "Label4": 163,
    "Label4_2": 164,
    "Label4_3": 165,
    "Label4_4": 166,
    "Label5": 140,
    "Label8": 67,
    "Label8_1": 68,
    "Label8_2": 29,
    "Label8_3": 30,
    "lblAddNewReq": 64,
    "lblAddNewReq_1": 7,
    "lblAddNewReq_2": 8,
    "lblAddNewReq_3": 9,
    "lblAddNewReq_4": 10,
    "lblAddNewReq_5": 23,
    "lblAddNewReq_6": 21,
    "lblAddNewReq_7": 39,
    "lblAddNewReq_8": 32,
    "lblCat": 44,
    "lblCataegory": 94,
    "lblCC_CCS": 43,
    "lblCostCode": 93,
    "lblDescr_CCS": 41,
    "lblDescription_1": 180,
    "lblDescription_2": 181,
    "lblDescription_3": 204,
    "lblDescription_4": 206,
    "lblDescription_5": 205,
    "lblDescription_6": 207,
    "lblDescription_7": 208,
    "lblDescription_8": 209,
    "lblDescription_9": 210,
    "lblManufacturer": 87,
    "lblPartNo": 86,
    "lblPartNo_1": 61,
    "lblPartNo_2": 63,
    "lblPartNo_3": 22,
    "lblPartNo_4": 24,
    "lblQty": 91,
    "lblReqDate": 99,
    "lblReqDescription": 81,
    "lblReqDescription_1": 17,
    "lblReqID": 79,
    "lblReqID_1": 15,
    "lblReqID_2": 13,
    "lblReqIDStatus": 82,
    "lblReqIDStatus_1": 18,
    "lblReqJObNo": 80,
    "lblReqJObNo_1": 16,
    "lblRequired": 100,
    "lblReset": 220,
    "lblUOM": 92,
    "lblWarning": 59,
    "lblWM_1": 201,
    "Library Screen": 185,
    "Main Screen": 52,
    "Messages Screen": 168,
    "Octagon1": 14,
    "rctCurrentReqItems": 58,
    "rctDivider": 19,
    "rctDivider_1": 38,
    "rctFooter_MS": 112,
    "rctMenu": 135,
    "rctMenu_5": 190,
    "rdSelectReqFillMethod": 57,
    "Rectangle1": 28,
    "Rectangle1_10": 20,
    "Rectangle1_4": 187,
    "Rectangle1_5": 170,
    "Rectangle1_6": 54,
    "Rectangle1_7": 83,
    "Rectangle1_8": 132,
    "Rectangle1_9": 5,
    "Rectangle2": 159,
    "Rectangle2_1": 160,
    "Rectangle2_2": 141,
    "Requisitions Screen": 130,
    "Title1": 37,
    "Title5": 144,
    "txtDeliveryLocEnter": 73,
    "txtDescription_CCS": 42,
    "txtDescriptionEntry": 222,
    "txtEmailInput": 173,
    "txtGalDescription": 90,
    "txtGalPartNo": 88,
    "txtGalQty": 95,
    "txtItemNoEntry": 217,
    "txtRJobNoEnter": 71,
    "txtSearchLibrary": 215
  },
  "FunctionParamsInvariantScripts": {},
  "HeaderLastSavedDateTimeUTC": "02/09/2022 13:10:29",
  "LocalDatabaseReferencesAsEmpty": false,
  "LocalResourceFileNames": {
    "RecProc": "fc4bcfc2-5661-4822-9055-95628c37eab0.png"
  },
  "LocalResourceRootPaths": {
    "RecProc": "https://docserverpwaprodwus.blob.core.windows.net/aae89c3c-1e33-4dd8-844c-4162ba6ce4b8-1/resource/Assets0Images0fc4bcfc2-5661-4822-9055-95628c37eab0.png?sv=2017-04-17&sr=b&sig=gN8cLR0vaygVLbbAD1uAcROjiXmFJsoJUyjrg5LFAwc%3D&spr=https&se=2022-02-10T12%3A01%3A54Z&sp=r"
  },
  "OldLogoFileName": "sqwhytsu.jpg",
  "OrderComponentMetadata": {},
  "OrderComponentTemplate": {},
  "OrderDataSource": {
    "colReqDetails": 10,
    "ComboBoxSample": 5,
    "CostCodeRequisition": 1,
    "CustomGallerySample": 3,
    "DropDownSample": 9,
    "MyFiles": 12,
    "RadioSample": 2,
    "ReqDetails": 6,
    "ReqHeader": 7,
    "ReqMessages": 8,
    "SendRequisitionMessages": 0,
    "TCReqLibrary": 4,
    "TempAttachmentsCol": 11
  },
  "OrderGroupControls": {
    "Group3": {
      "btnSaveLibRec": 3,
      "dd_Revision": 1,
      "icnSave": 2,
      "lblReset": 4,
      "txtDescriptionEntry": 5,
      "txtItemNoEntry": 0
    },
    "grp_AddREqDetails": {
      "btnSave_8": 0,
      "Image8_4": 1
    },
    "grp_Header_LS": {
      "Image1_1": 0,
      "Label1_1": 2,
      "Rectangle1_4": 1
    },
    "grp_Header_LS_1": {
      "Image1_2": 0,
      "Label1_2": 2,
      "Rectangle1_5": 1
    },
    "grp_Header_MS": {
      "Image1_8": 0,
      "Image14_3": 3,
      "Label1_6": 2,
      "Rectangle1_6": 1
    },
    "grp_Header_RS_1": {
      "Image1_3": 0,
      "Label1_3": 2,
      "Rectangle1_8": 1
    },
    "grp_Header_RS_2": {
      "Image1_6": 0,
      "Label1_4": 2,
      "Rectangle1_9": 1
    },
    "grp_SendEmail": {
      "btnSave_2": 0,
      "Image8": 1,
      "Label2_3": 2
    },
    "grp_SendEmail_1": {
      "btnSave_3": 0,
      "Image8_1": 1,
      "Label2_7": 2
    },
    "grp_SendEmail_2": {
      "btnSave_4": 0,
      "Image8_2": 1,
      "Label2_8": 2
    },
    "grpAddReq": {
      "btnSave_7": 0,
      "Image8_3": 1,
      "Label2": 2
    },
    "grpAddReqDetails": {
      "btnSave_15": 1,
      "Image8_6": 2,
      "Label2_1": 0
    },
    "grpCloseAttach": {
      "btnSave_14": 0,
      "Icon1_11": 1,
      "Label3_5": 2
    },
    "grpGTLib_MS": {
      "btnSave_11": 0,
      "Image1_10": 2,
      "Label3_3": 1
    },
    "grpGTReq_MS": {
      "btnSave_10": 0,
      "Image1_9": 2,
      "Label3_2": 1
    },
    "grpSaveReq": {
      "btnSave_9": 0,
      "Icon1_10": 1,
      "Label3_4": 2
    },
    "grpSaveReqDetails": {
      "btnSave_12": 2,
      "Image1": 0,
      "Label1": 1
    },
    "grpSaveStatus_4": {
      "btnSave_13": 1,
      "Image8_5": 2,
      "Label1_8": 0
    },
    "grpSearch": {
      "icnSearch": 0,
      "txtSearchLibrary": 1
    }
  },
  "OrderTemplate": {},
  "OrderXMLTemplate": {
    "attachments": 13,
    "button": 7,
    "checkbox": 14,
    "combobox": 10,
    "datepicker": 11,
    "dropdown": 5,
    "form": 12,
    "gallery": 3,
    "icon": 9,
    "image": 0,
    "label": 2,
    "octagon": 4,
    "radio": 8,
    "rectangle": 1,
    "text": 6
  },
  "PublishOrderIndices": {
    "App": 0,
    "Attachments_DataCard2": 54,
    "Body4_1": 96,
    "Body4_10": 94,
    "Body4_2": 104,
    "Body4_3": 103,
    "Body4_4": 92,
    "Body4_5": 100,
    "Body4_6": 91,
    "Body4_7": 97,
    "Body4_8": 101,
    "Body4_9": 93,
    "btnSave_1": 99,
    "btnSave_10": 65,
    "btnSave_11": 67,
    "btnSave_12": 124,
    "btnSave_13": 62,
    "btnSave_14": 56,
    "btnSave_15": 219,
    "btnSave_2": 167,
    "btnSave_3": 115,
    "btnSave_4": 115,
    "btnSave_7": 22,
    "btnSave_8": 24,
    "btnSave_9": 69,
    "btnSaveLibRec": 155,
    "Button1": 83,
    "Button1_1": 133,
    "CB_Responsible": 20,
    "chkSelectItem": 134,
    "Cost Code Screen": 0,
    "dcAttachments": 55,
    "dd_Revision": 154,
    "dpDalReqDate": 51,
    "drpgalCat": 48,
    "drpgalCat_CCS": 218,
    "drpgalCostCode": 47,
    "drpgalCostCode_CCS": 217,
    "drpgalReq": 52,
    "drpgalUOM": 46,
    "drpgalUOM_4": 130,
    "drpgalUOM_5": 147,
    "drpgalUOM_6": 148,
    "drpgalVendor": 39,
    "drpgalVendor_CCS": 212,
    "frmAttachments": 53,
    "galAddReqItems": 34,
    "galAvailableReqItems": 13,
    "galAvailableReqItems_1": 198,
    "galCCAttachments": 179,
    "Gallery2": 205,
    "galleryTemplate1": 180,
    "galleryTemplate1_1": 170,
    "galleryTemplate2": 132,
    "galleryTemplate3": 206,
    "galleryTemplate5": 82,
    "galleryTemplate6": 108,
    "galleryTemplate7": 35,
    "galleryTemplate8": 14,
    "galleryTemplate8_1": 199,
    "galLibraryItems": 131,
    "galMessages": 169,
    "galReqDetails": 107,
    "galRequisitions": 81,
    "Group3": 153,
    "grp_AddREqDetails": 25,
    "grp_Header_LS": 119,
    "grp_Header_LS_1": 160,
    "grp_Header_MS": 1,
    "grp_Header_RS_1": 78,
    "grp_Header_RS_2": 176,
    "grp_SendEmail": 165,
    "grp_SendEmail_1": 114,
    "grp_SendEmail_2": 114,
    "grpAddReq": 23,
    "grpAddReqDetails": 220,
    "grpCloseAttach": 57,
    "grpGTLib_MS": 68,
    "grpGTReq_MS": 66,
    "grpSaveReq": 70,
    "grpSaveReqDetails": 125,
    "grpSaveStatus_4": 59,
    "grpSearch": 150,
    "icnAddItems": 122,
    "icnAddNewReq": 10,
    "icnCollapse": 88,
    "icnCollapse_Lib": 137,
    "icnExpand": 87,
    "icnExpand_Lib": 136,
    "icnSave": 157,
    "icnSearch": 151,
    "Icon1_10": 73,
    "Icon1_11": 58,
    "Image1": 128,
    "Image1_1": 118,
    "Image1_10": 72,
    "Image1_2": 159,
    "Image1_3": 77,
    "Image1_6": 175,
    "Image1_8": 0,
    "Image1_9": 71,
    "Image10": 84,
    "Image14_3": 4,
    "Image2_1": 126,
    "Image2_2": 90,
    "Image3": 207,
    "Image3_1": 208,
    "Image4": 197,
    "Image6": 95,
    "Image6_1": 98,
    "Image6_2": 102,
    "Image8": 166,
    "Image8_1": 116,
    "Image8_2": 116,
    "Image8_3": 27,
    "Image8_4": 28,
    "Image8_5": 61,
    "Image8_6": 221,
    "Image9": 171,
    "Image9_1": 174,
    "imd_DelRec": 17,
    "imd_DelRec_1": 18,
    "imd_DelRec_2": 203,
    "imgShowCurrentReqDetails": 8,
    "Label1": 129,
    "Label1_1": 121,
    "Label1_2": 162,
    "Label1_3": 80,
    "Label1_4": 178,
    "Label1_6": 3,
    "Label1_8": 60,
    "Label2": 26,
    "Label2_1": 222,
    "Label2_2": 163,
    "Label2_3": 168,
    "Label2_4": 127,
    "Label2_5": 145,
    "Label2_6": 146,
    "Label2_7": 117,
    "Label2_8": 117,
    "Label3_2": 74,
    "Label3_3": 75,
    "Label3_4": 76,
    "Label3_5": 63,
    "Label4": 109,
    "Label4_2": 110,
    "Label4_3": 111,
    "Label4_4": 112,
    "Label5": 85,
    "Label8": 15,
    "Label8_1": 16,
    "Label8_2": 201,
    "Label8_3": 202,
    "lblAddNewReq": 12,
    "lblAddNewReq_1": 182,
    "lblAddNewReq_2": 183,
    "lblAddNewReq_3": 184,
    "lblAddNewReq_4": 185,
    "lblAddNewReq_5": 195,
    "lblAddNewReq_6": 193,
    "lblAddNewReq_7": 211,
    "lblAddNewReq_8": 204,
    "lblCat": 216,
    "lblCataegory": 44,
    "lblCC_CCS": 215,
    "lblCostCode": 43,
    "lblDescr_CCS": 213,
    "lblDescription_1": 172,
    "lblDescription_2": 173,
    "lblDescription_3": 138,
    "lblDescription_4": 140,
    "lblDescription_5": 139,
    "lblDescription_6": 141,
    "lblDescription_7": 142,
    "lblDescription_8": 143,
    "lblDescription_9": 144,
    "lblManufacturer": 37,
    "lblPartNo": 36,
    "lblPartNo_1": 9,
    "lblPartNo_2": 11,
    "lblPartNo_3": 194,
    "lblPartNo_4": 196,
    "lblQty": 41,
    "lblReqDate": 49,
    "lblReqDescription": 31,
    "lblReqDescription_1": 189,
    "lblReqID": 29,
    "lblReqID_1": 187,
    "lblReqID_2": 181,
    "lblReqIDStatus": 32,
    "lblReqIDStatus_1": 190,
    "lblReqJObNo": 30,
    "lblReqJObNo_1": 188,
    "lblRequired": 50,
    "lblReset": 156,
    "lblUOM": 42,
    "lblWarning": 7,
    "lblWM_1": 135,
    "Library Screen": 0,
    "Main Screen": 0,
    "Messages Screen": 0,
    "Octagon1": 186,
    "rctCurrentReqItems": 6,
    "rctDivider": 191,
    "rctDivider_1": 210,
    "rctFooter_MS": 64,
    "rctMenu": 113,
    "rctMenu_5": 123,
    "rdSelectReqFillMethod": 5,
    "Rectangle1": 200,
    "Rectangle1_10": 192,
    "Rectangle1_4": 120,
    "Rectangle1_5": 161,
    "Rectangle1_6": 2,
    "Rectangle1_7": 33,
    "Rectangle1_8": 79,
    "Rectangle1_9": 177,
    "Rectangle2": 105,
    "Rectangle2_1": 106,
    "Rectangle2_2": 86,
    "Requisitions Screen": 0,
    "Title1": 209,
    "Title5": 89,
    "txtDeliveryLocEnter": 21,
    "txtDescription_CCS": 214,
    "txtDescriptionEntry": 158,
    "txtEmailInput": 164,
    "txtGalDescription": 40,
    "txtGalPartNo": 38,
    "txtGalQty": 45,
    "txtItemNoEntry": 152,
    "txtRJobNoEnter": 19,
    "txtSearchLibrary": 149
  },
  "ResourcesJsonIndices": {
    "Image-RecProc": 0,
    "Image-SampleImage": 1
  },
  "TemplateVersions": {},
  "VolatileProperties": {
    "AnalysisLoadTime": 1.9544815,
    "ControlCount": {
      "attachments": 1,
      "button": 16,
      "checkbox": 1,
      "combobox": 2,
      "datepicker": 1,
      "dropdown": 11,
      "form": 1,
      "gallery": 9,
      "galleryTemplate": 9,
      "group": 19,
      "icon": 10,
      "image": 32,
      "label": 87,
      "octagon": 1,
      "radio": 1,
      "rectangle": 17,
      "screen": 5,
      "text": 10,
      "typedDataCard": 1
    },
    "DeserializationLoadTime": 3.8133351,
    "ErrorCount": 6
  }
}